arviz_base/__init__.py
arviz_base/__init__.pyi
arviz_base/_version.py
arviz_base/_version.pyi
arviz_base/base.py
arviz_base/base.pyi
arviz_base/citations.py
arviz_base/citations.pyi
arviz_base/converters.py
arviz_base/converters.pyi
arviz_base/datasets.py
arviz_base/datasets.pyi
arviz_base/io_cmdstanpy.py
arviz_base/io_cmdstanpy.pyi
arviz_base/io_dict.py
arviz_base/io_dict.pyi
arviz_base/io_emcee.py
arviz_base/io_emcee.pyi
arviz_base/io_numpyro.py
arviz_base/io_numpyro.pyi
arviz_base/io_pystan.py
arviz_base/io_pystan.pyi
arviz_base/labels.py
arviz_base/labels.pyi
arviz_base/py.typed
arviz_base/rcparams.py
arviz_base/rcparams.pyi
arviz_base/references.bib
arviz_base/reorg.py
arviz_base/reorg.pyi
arviz_base/sel_utils.py
arviz_base/sel_utils.pyi
arviz_base/testing.py
arviz_base/testing.pyi
arviz_base/transform.py
arviz_base/transform.pyi
arviz_base/types.py
arviz_base/types.pyi
arviz_base/utils.py
arviz_base/utils.pyi
arviz_base/example_data/.gitignore
arviz_base/example_data/LICENSE
arviz_base/example_data/README.md
arviz_base/example_data/data_local.json
arviz_base/example_data/data_remote.json
arviz_base/example_data/data/centered_eight.nc
arviz_base/example_data/data/non_centered_eight.nc
arviz_base-0.8.2.dist-info/licenses/LICENSE
arviz_base-0.8.2.dist-info/WHEEL
arviz_base-0.8.2.dist-info/METADATA
arviz_base-0.8.2.dist-info/RECORD
