Metadata-Version: 2.4
Name: arviz-base
Version: 0.8.2
Summary: Base ArviZ features and converters.
Author-email: ArviZ team <arvizdevs@gmail.com>
Requires-Python: >=3.11
Classifier: Development Status :: 3 - Alpha
Classifier: Intended Audience :: Developers
Classifier: Intended Audience :: Science/Research
Classifier: Intended Audience :: Education
Classifier: License :: OSI Approved :: Apache Software License
Classifier: Operating System :: OS Independent
Classifier: Programming Language :: Python
Classifier: Programming Language :: Python :: 3
Classifier: Programming Language :: Python :: 3.11
Classifier: Programming Language :: Python :: 3.12
Classifier: Programming Language :: Python :: 3.13
License-File: LICENSE
Requires-Dist: numpy>=1.24
Requires-Dist: xarray>=2024.11.0
Requires-Dist: typing-extensions>=3.10
Requires-Dist: build ; extra == "check"
Requires-Dist: pre-commit ; extra == "check"
Requires-Dist: docstub==0.4 ; extra == "check"
Requires-Dist: mypy ; extra == "check"
Requires-Dist: isort ; extra == "check"
Requires-Dist: black ; extra == "check"
Requires-Dist: pre-commit ; extra == "ci"
Requires-Dist: cloudpickle ; extra == "ci"
Requires-Dist: sphinx-book-theme ; extra == "doc"
Requires-Dist: myst-parser[linkify] ; extra == "doc"
Requires-Dist: myst-nb ; extra == "doc"
Requires-Dist: sphinx-copybutton ; extra == "doc"
Requires-Dist: numpydoc ; extra == "doc"
Requires-Dist: sphinx>=5 ; extra == "doc"
Requires-Dist: sphinx-design ; extra == "doc"
Requires-Dist: jupyter-sphinx ; extra == "doc"
Requires-Dist: h5netcdf[h5py] ; extra == "doc"
Requires-Dist: h5netcdf[h5py] ; extra == "h5netcdf"
Requires-Dist: netcdf4 ; extra == "netcdf4"
Requires-Dist: xarray!=2025.8.0 ; extra == "test"
Requires-Dist: pytest ; extra == "test"
Requires-Dist: pytest-cov ; extra == "test"
Requires-Dist: scipy ; extra == "test"
Requires-Dist: zarr ; extra == "zarr"
Project-URL: documentation, https://arviz-base.readthedocs.io
Project-URL: funding, https://opencollective.com/arviz
Project-URL: source, https://github.com/arviz-devs/arviz-base
Project-URL: tracker, https://github.com/arviz-devs/arviz-base/issues
Provides-Extra: check
Provides-Extra: ci
Provides-Extra: doc
Provides-Extra: h5netcdf
Provides-Extra: netcdf4
Provides-Extra: test
Provides-Extra: zarr
